README.md
setup.cfg
setup.py
eventdispatcher/__init__.py
eventdispatcher/clock.py
eventdispatcher/dictproperty.py
eventdispatcher/eventdispatcher.py
eventdispatcher/exceptions.py
eventdispatcher/json_map.py
eventdispatcher/limitproperty.py
eventdispatcher/listproperty.py
eventdispatcher/optionproperty.py
eventdispatcher/property.py
eventdispatcher/scheduledevent.py
eventdispatcher/setproperty.py
eventdispatcher/stringproperty.py
eventdispatcher/unitproperty.py
eventdispatcher/version.py
eventdispatcher/weakrefproperty.py
eventdispatcher.egg-info/PKG-INFO
eventdispatcher.egg-info/SOURCES.txt
eventdispatcher.egg-info/dependency_links.txt
eventdispatcher.egg-info/requires.txt
eventdispatcher.egg-info/top_level.txt