Metadata-Version: 1.1
Name: eventdispatcher
Version: 1.9.0
Summary: An event dispatcher framework inspired by the Kivy project.
Home-page: https://github.com/lobocv/eventdispatcher
Author: Calvin Lobo
Author-email: calvinvlobo@gmail.com
License: UNKNOWN
Download-URL: https://github.com/lobocv/eventdispatcher/tarball/1.9.0
Keywords: event,dispatcher,dispatching,kivy,observer,framework,property,properties
Platform: UNKNOWN
